{
	"SIN": {
		"airport_code": "SIN",
		"airport_name": "Singapore Changi Airport",
		"city_name": "Singapore",
		"country_code": "SG",
		"country_name": "Singapore",
		"elevation": 22,
		"latitude": "1.361173",
		"longitude": "103.990201",
		"timezone": "Asia/Singapore",
		"routes": [
			{
				"airport_code": "JHB",
				"distance": 32,
				"duration": 10,
				"base_price": 103,
				"airlines": [
					{
						"airline_code": "SQ",
						"airline_name": "Singapore Airlines"
					},
					{
						"airline_code": "MH",
						"airline_name": "Malaysia Airlines"
					}
				]
			},
			{
				"airport_code": "BKK",
				"distance": 1435,
				"duration": 125,
				"base_price": 243,
				"airlines": [
					{
						"airline_code": "TG",
						"airline_name": "Thai Airways"
					},
					{
						"airline_code": "SQ",
						"airline_name": "Singapore Airlines"
					}
				]
			},
			{
				"airport_code": "HKG",
				"distance": 3115,
				"duration": 275,
				"base_price": 411,
				"airlines": [
					{
						"airline_code": "SQ",
						"airline_name": "Singapore Airlines"
					}
				]
			},
			{
				"airport_code": "DEL",
				"distance": 3880,
				"duration": 330,
				"base_price": 488,
				"airlines": [
					{
						"airline_code": "AI",
						"airline_name": "Air India"
					},
					{
						"airline_code": "SQ",
						"airline_name": "Singapore Airlines"
					}
				]
			},
			{
				"airport_code": "DXB",
				"distance": 5850,
				"duration": 480,
				"base_price":685,
				"airlines": [
					{
						"airline_code": "EK",
						"airline_name": "Emirates"
					},
					{
						"airline_code": "SQ",
						"airline_name": "Singapore Airlines"
					}
				]

			}
		]
	},
	"JHB": {
		"airport_code": "JHB",
		"airport_name": "Sultan Ismail",
		"city_name": "Johor Bharu",
		"country_code": "MY",
		"country_name": "Malaysia",
		"elevation": 135,
		"latitude": "1.63668",
		"longitude": "103.667959",
		"timezone": "Asia/Kuala_Lumpur",
		"routes": [
			{
				"airport_code": "SIN",
				"distance": 32,
				"duration": 10,
				"base_price": 103,
				"airlines": [
					{
						"airline_code": "SQ",
						"airline_name": "Singapore Airlines"
					},
					{
						"airline_code": "MH",
						"airline_name": "Malaysia Airlines"
					}
				]
			}
		]
	},
	"KUL": {
		"airport_code": "KUL",
		"airport_name": "Kuala Lumpur International Airport",
		"city_name": "Kuala Lumpur",
		"country_code": "MY",
		"country_name": "Malaysia",
		"elevation": 70,
		"latitude": "2.7456",
		"longitude": "101.7092",
		"timezone": "Asia/Kuala_Lumpur",
		"routes": [
			{
				"airport_code": "SIN",
				"distance": 299,
				"duration": 60,
				"base_price": 129,
				"airlines": [
					{
						"airline_code": "MH",
						"airline_name": "Malaysia Airlines"
					},
					{
						"airline_code": "SQ",
						"airline_name": "Singapore Airlines"
					}
				]
			},
			{
				"airport_code": "CGK",
				"distance": 1128,
				"duration": 120,
				"base_price": 212,
				"airlines": [
					{
						"airline_code": "MH",
						"airline_name": "Malaysia Airlines"
					},
					{
						"airline_code": "GA",
						"airline_name": "Garuda Indonesia"
					}
				]
			}
		]
	},
	"BKK": {
		"airport_code": "BKK",
		"airport_name": "Suvarnabhumi Airport",
		"city_name": "Bangkok",
		"country_code": "TH",
		"country_name": "Thailand",
		"elevation": 5,
		"latitude": "13.6890",
		"longitude": "100.7501",
		"timezone": "Asia/Bangkok",
		"routes": [
			{
				"airport_code": "SIN",
				"distance": 1435,
				"duration": 125,
				"base_price": 243,
				"airlines": [
					{
						"airline_code": "TG",
						"airline_name": "Thai Airways"
					},
					{
						"airline_code": "SQ",
						"airline_name": "Singapore Airlines"
					}
				]
			},
			{
				"airport_code": "HKG",
				"distance": 1680,
				"duration": 150,
				"base_price": 268,
				"airlines": [
					{
						"airline_code": "TG",
						"airline_name": "Thai Airways"
					},
					{
						"airline_code": "CX",
						"airline_name": "Cathay Pacific"
					}
				]
			},
			{
				"airport_code": "DEL",
				"distance": 2580,
				"duration": 210,
				"base_price": 358,
				"airlines": [
					{
						"airline_code": "AI",
						"airline_name": "Air India"
					},
					{
						"airline_code": "TG",
						"airline_name": "Thai Airways"
					}
				]
			}
		]
	},
	"CGK": {
		"airport_code": "CGK",
		"airport_name": "Soekarno-Hatta International Airport",
		"city_name": "Jakarta",
		"country_code": "ID",
		"country_name": "Indonesia",
		"elevation": 10,
		"latitude": "-6.1256",
		"longitude": "106.6559",
		"timezone": "Asia/Jakarta",
		"routes": [
			{
				"airport_code": "KUL",
				"distance": 1128,
				"duration": 120,
				"base_price": 212,
				"airlines": [
					{
						"airline_code": "GA",
						"airline_name": "Garuda Indonesia"
					},
					{
						"airline_code": "MH",
						"airline_name": "Malaysia Airlines"
					}
				]
			},
			{
				"airport_code": "DPS",
				"distance": 983,
				"duration": 110,
				"base_price": 198,
				"airlines": [
					{
						"airline_code": "GA",
						"airline_name": "Garuda Indonesia"
					},
					{
						"airline_code": "QZ",
						"airline_name": "Indonesia AirAsia"
					}
				]
			}
		]
	},
	"HKG": {
		"airport_code": "HKG",
		"airport_name": "Hong Kong International Airport",
		"city_name": "Hong Kong",
		"country_code": "HK",
		"country_name": "Hong Kong",
		"elevation": 9,
		"latitude": "22.3080",
		"longitude": "113.9185",
		"timezone": "Asia/Hong_Kong",
		"routes": [
			{
				"airport_code": "BKK",
				"distance": 1680,
				"duration": 150,
				"base_price": 268,
				"airlines": [
					{
						"airline_code": "CX",
						"airline_name": "Cathay Pacific"
					},
					{
						"airline_code": "TG",
						"airline_name": "Thai Airways"
					}
				]
			},
			{
				"airport_code": "NRT",
				"distance": 2960,
				"duration": 240,
				"base_price": 396,
				"airlines": [
					{
						"airline_code": "CX",
						"airline_name": "Cathay Pacific"
					},
					{
						"airline_code": "JL",
						"airline_name": "Japan Airlines"
					}
				]
			},
			{
				"airport_code": "SIN",
				"distance": 3115,
				"duration": 275,
				"base_price": 411,
				"airlines": [
					{
						"airline_code": "SQ",
						"airline_name": "Singapore Airlines"
					}
				]
			},
			{
				"airport_code": "PEK",
				"distance": 1970,
				"duration": 180,
				"base_price": 296,
				"airlines": [
					{
						"airline_code": "CA",
						"airline_name": "Air China"
					},
					{
						"airline_code": "CX",
						"airline_name": "Cathay Pacific"
					}
				]
			},
			{
				"airport_code": "ICN",
				"distance": 2060,
				"duration": 180,
				"base_price": 306,
				"airlines": [
					{
						"airline_code": "KE",
						"airline_name": "Korean Air"
					},
					{
						"airline_code": "CX",
						"airline_name": "Cathay Pacific"
					}
				]
			}
		]
	},
	"DPS": {
		"airport_code": "DPS",
		"airport_name": "Ngurah Rai International Airport",
		"city_name": "Denpasar",
		"country_code": "ID",
		"country_name": "Indonesia",
		"elevation": 14,
		"latitude": "-8.7481",
		"longitude": "115.1675",
		"timezone": "Asia/Makassar",
		"routes": [
			{
				"airport_code": "CGK",
				"distance": 983,
				"duration": 110,
				"base_price": 198,
				"airlines": [
					{
						"airline_code": "GA",
						"airline_name": "Garuda Indonesia"
					},
					{
						"airline_code": "QZ",
						"airline_name": "Indonesia AirAsia"
					}
				]
			},
			{
				"airport_code": "SYD",
				"distance": 4600,
				"duration": 360,
				"base_price": 560,
				"airlines": [
					{
						"airline_code": "QF",
						"airline_name": "Qantas"
					},
					{
						"airline_code": "VA",
						"airline_name": "Virgin Australia"
					}
				]
			}
		]
	},
	"NRT": {
		"airport_code": "NRT",
		"airport_name": "Narita International Airport",
		"city_name": "Tokyo",
		"country_code": "JP",
		"country_name": "Japan",
		"elevation": 141,
		"latitude": "35.7719",
		"longitude": "140.3929",
		"timezone": "Asia/Tokyo",
		"routes": [
			{
				"airport_code": "LAX",
				"distance": 8770,
				"duration": 660,
				"base_price": 977,
				"airlines": [
					{
						"airline_code": "NH",
						"airline_name": "All Nippon Airways"
					},
					{
						"airline_code": "JL",
						"airline_name": "Japan Airlines"
					}
				]
			},
			{
				"airport_code": "SIN",
				"distance": 5340,
				"duration": 420,
				"base_price": 634,
				"airlines": [
					{
						"airline_code": "SQ",
						"airline_name": "Singapore Airlines"
					},
					{
						"airline_code": "JL",
						"airline_name": "Japan Airlines"
					}
				]
			},
			{
				"airport_code": "ICN",
				"distance": 1160,
				"duration": 120,
				"base_price": 218,
				"airlines": [
					{
						"airline_code": "KE",
						"airline_name": "Korean Air"
					},
					{
						"airline_code": "JL",
						"airline_name": "Japan Airlines"
					}
				]
			},
			{
				"airport_code": "PEK",
				"distance": 2100,
				"duration": 195,
				"base_price": 316,
				"airlines": [
					{
						"airline_code": "CA",
						"airline_name": "Air China"
					},
					{
						"airline_code": "NH",
						"airline_name": "All Nippon Airways"
					}
				]
			}
		]
	},
	"SYD": {
		"airport_code": "SYD",
		"airport_name": "Sydney Kingsford Smith Airport",
		"city_name": "Sydney",
		"country_code": "AU",
		"country_name": "Australia",
		"elevation": 21,
		"latitude": "-33.9399",
		"longitude": "151.1753",
		"timezone": "Australia/Sydney",
		"routes": [
			{
				"airport_code": "LAX",
				"distance": 12051,
				"duration": 900,
				"base_price": 1305,
				"airlines": [
					{
						"airline_code": "QF",
						"airline_name": "Qantas"
					},
					{
						"airline_code": "UA",
						"airline_name": "United Airlines"
					}
				]
			},
			{
				"airport_code": "DPS",
				"distance": 4600,
				"duration": 360,
				"base_price": 560,
				"airlines": [
					{
						"airline_code": "QF",
						"airline_name": "Qantas"
					},
					{
						"airline_code": "VA",
						"airline_name": "Virgin Australia"
					}
				]
			}
		]
	},
	"LAX": {
		"airport_code": "LAX",
		"airport_name": "Los Angeles International Airport",
		"city_name": "Los Angeles",
		"country_code": "US",
		"country_name": "United States",
		"elevation": 125,
		"latitude": "33.9416",
		"longitude": "-118.4085",
		"timezone": "America/Los_Angeles",
		"routes": [
			{
				"airport_code": "NRT",
				"distance": 8770,
				"duration": 660,
				"base_price": 977,
				"airlines": [
					{
						"airline_code": "NH",
						"airline_name": "All Nippon Airways"
					},
					{
						"airline_code": "JL",
						"airline_name": "Japan Airlines"
					}
				]
			}
		]
	},
	"DEL": {
		"airport_code": "DEL",
		"airport_name": "Indira Gandhi International Airport",
		"city_name": "New Delhi",
		"country_code": "IN",
		"country_name": "India",
		"elevation": 237,
		"latitude": "28.5562",
		"longitude": "77.1000",
		"timezone": "Asia/Kolkata",
		"routes": [
			{
				"airport_code": "SIN",
				"distance": 3880,
				"duration": 330,
				"base_price": 488,
				"airlines": [
					{
						"airline_code": "AI",
						"airline_name": "Air India"
					},
					{
						"airline_code": "SQ",
						"airline_name": "Singapore Airlines"
					}
				]
			},
			{
				"airport_code": "BKK",
				"distance": 2580,
				"duration": 210,
				"base_price": 358,
				"airlines": [
					{
						"airline_code": "AI",
						"airline_name": "Air India"
					},
					{
						"airline_code": "TG",
						"airline_name": "Thai Airways"
					}
				]
			},
			{
				"airport_code": "DXB",
				"distance": 2200,
				"duration": 210,
				"base_price": 326,
				"airlines": [
					{
						"airline_code": "EK",
						"airline_name": "Emirates"
					},
					{
						"airline_code": "AI",
						"airline_name": "Air India"
					}
				]
			}
		]
	},
	"ICN": {
		"airport_code": "ICN",
		"airport_name": "Incheon International Airport",
		"city_name": "Seoul",
		"country_code": "KR",
		"country_name": "South Korea",
		"elevation": 23,
		"latitude": "37.4602",
		"longitude": "126.4407",
		"timezone": "Asia/Seoul",
		"routes": [
			{
				"airport_code": "NRT",
				"distance": 1160,
				"duration": 120,
				"base_price": 218,
				"airlines": [
					{
						"airline_code": "KE",
						"airline_name": "Korean Air"
					},
					{
						"airline_code": "JL",
						"airline_name": "Japan Airlines"
					}
				]
			},
			{
				"airport_code": "HKG",
				"distance": 2060,
				"duration": 180,
				"base_price": 306,
				"airlines": [
					{
						"airline_code": "KE",
						"airline_name": "Korean Air"
					},
					{
						"airline_code": "CX",
						"airline_name": "Cathay Pacific"
					}
				]
			}
		]
	},
	"PEK": {
		"airport_code": "PEK",
		"airport_name": "Beijing Capital International Airport",
		"city_name": "Beijing",
		"country_code": "CN",
		"country_name": "China",
		"elevation": 116,
		"latitude": "40.0799",
		"longitude": "116.6031",
		"timezone": "Asia/Shanghai",
		"routes": [
			{
				"airport_code": "HKG",
				"distance": 1970,
				"duration": 180,
				"base_price": 296,
				"airlines": [
					{
						"airline_code": "CA",
						"airline_name": "Air China"
					},
					{
						"airline_code": "CX",
						"airline_name": "Cathay Pacific"
					}
				]
			},
			{
				"airport_code": "NRT",
				"distance": 2100,
				"duration": 195,
				"base_price": 316,
				"airlines": [
					{
						"airline_code": "CA",
						"airline_name": "Air China"
					},
					{
						"airline_code": "NH",
						"airline_name": "All Nippon Airways"
					}
				]
			}
		]
	},
	"DXB": {
		"airport_code": "DXB",
		"airport_name": "Dubai International Airport",
		"city_name": "Dubai",
		"country_code": "AE",
		"country_name": "United Arab Emirates",
		"elevation": 62,
		"latitude": "25.2532",
		"longitude": "55.3657",
		"timezone": "Asia/Dubai",
		"routes": [
			{
				"airport_code": "SIN",
				"distance": 5850,
				"duration": 480,
				"base_price": 685,
				"airlines": [
					{
						"airline_code": "EK",
						"airline_name": "Emirates"
					},
					{
						"airline_code": "SQ",
						"airline_name": "Singapore Airlines"
					}
				]
			},
			{
				"airport_code": "DEL",
				"distance": 2200,
				"duration": 210,
				"base_price": 326,
				"airlines": [
					{
						"airline_code": "EK",
						"airline_name": "Emirates"
					},
					{
						"airline_code": "AI",
						"airline_name": "Air India"
					}
				]
			}
		]
	}
}